{"OIL": [{"TRADE_DT": "20260723", "PRODCD": "B034", "PRODNM": "고급휘발유", "PRICE": "2347.31", "DIFF": "-0.59"}, {"TRADE_DT": "20260723", "PRODCD": "B027", "PRODNM": "휘발유", "PRICE": "1871.49", "DIFF": "-0.25"}, {"TRADE_DT": "20260723", "PRODCD": "D047", "PRODNM": "자동차용경유", "PRICE": "1855.81", "DIFF": "-0.56"}, {"TRADE_DT": "20260723", "PRODCD": "C004", "PRODNM": "실내등유", "PRICE": "1590.57", "DIFF": "-0.25"}, {"TRADE_DT": "20260723", "PRODCD": "K015", "PRODNM": "자동차용부탄", "PRICE": "1135.56", "DIFF": "-0.05"}], "URL": "https://place.map.kakao.com/main/v/{}?_={}"}