{"OIL": [{"TRADE_DT": "20220515", "PRODCD": "B034", "PRODNM": "고급휘발유", "PRICE": "2175.97", "DIFF": "-0.19"}, {"TRADE_DT": "20220515", "PRODCD": "D047", "PRODNM": "자동차용경유", "PRICE": "1965.46", "DIFF": "+1.44"}, {"TRADE_DT": "20220515", "PRODCD": "B027", "PRODNM": "휘발유", "PRICE": "1955.74", "DIFF": "+1.04"}, {"TRADE_DT": "20220515", "PRODCD": "C004", "PRODNM": "실내등유", "PRICE": "1477.80", "DIFF": "+1.98"}, {"TRADE_DT": "20220515", "PRODCD": "K015", "PRODNM": "자동차용부탄", "PRICE": "1134.04", "DIFF": "-0.11"}], "URL": "https://place.map.kakao.com/main/v/{}?_={}"}