{"OIL": [{"TRADE_DT": "20230531", "PRODCD": "B034", "PRODNM": "고급휘발유", "PRICE": "1870.64", "DIFF": "-0.25"}, {"TRADE_DT": "20230531", "PRODCD": "B027", "PRODNM": "휘발유", "PRICE": "1598.71", "DIFF": "-0.88"}, {"TRADE_DT": "20230531", "PRODCD": "D047", "PRODNM": "자동차용경유", "PRICE": "1420.34", "DIFF": "-1.94"}, {"TRADE_DT": "20230531", "PRODCD": "C004", "PRODNM": "실내등유", "PRICE": "1354.28", "DIFF": "-1.01"}, {"TRADE_DT": "20230531", "PRODCD": "K015", "PRODNM": "자동차용부탄", "PRICE": "987.68", "DIFF": "-0.12"}], "URL": "https://place.map.kakao.com/main/v/{}?_={}"}