{"OIL": [{"TRADE_DT": "20220728", "PRODCD": "B034", "PRODNM": "고급휘발유", "PRICE": "2181.95", "DIFF": "-6.35"}, {"TRADE_DT": "20220728", "PRODCD": "D047", "PRODNM": "자동차용경유", "PRICE": "2001.23", "DIFF": "-5.51"}, {"TRADE_DT": "20220728", "PRODCD": "B027", "PRODNM": "휘발유", "PRICE": "1920.53", "DIFF": "-6.28"}, {"TRADE_DT": "20220728", "PRODCD": "C004", "PRODNM": "실내등유", "PRICE": "1675.38", "DIFF": "-1.06"}, {"TRADE_DT": "20220728", "PRODCD": "K015", "PRODNM": "자동차용부탄", "PRICE": "1099.24", "DIFF": "-0.15"}], "URL": "https://place.map.kakao.com/main/v/{}?_={}"}