{"OIL": [{"TRADE_DT": "20230310", "PRODCD": "B034", "PRODNM": "고급휘발유", "PRICE": "1854.14", "DIFF": "-0.11"}, {"TRADE_DT": "20230310", "PRODCD": "B027", "PRODNM": "휘발유", "PRICE": "1592.07", "DIFF": "+0.87"}, {"TRADE_DT": "20230310", "PRODCD": "D047", "PRODNM": "자동차용경유", "PRICE": "1548.14", "DIFF": "-0.81"}, {"TRADE_DT": "20230310", "PRODCD": "C004", "PRODNM": "실내등유", "PRICE": "1432.79", "DIFF": "-0.30"}, {"TRADE_DT": "20230310", "PRODCD": "K015", "PRODNM": "자동차용부탄", "PRICE": "989.15", "DIFF": "-0.28"}], "URL": "https://place.map.kakao.com/main/v/{}?_={}"}