{"OIL": [{"TRADE_DT": "20260305", "PRODCD": "B034", "PRODNM": "고급휘발유", "PRICE": "2022.58", "DIFF": "+23.37"}, {"TRADE_DT": "20260305", "PRODCD": "B027", "PRODNM": "휘발유", "PRICE": "1807.12", "DIFF": "+29.64"}, {"TRADE_DT": "20260305", "PRODCD": "D047", "PRODNM": "자동차용경유", "PRICE": "1785.31", "DIFF": "+56.54"}, {"TRADE_DT": "20260305", "PRODCD": "C004", "PRODNM": "실내등유", "PRICE": "1375.62", "DIFF": "+17.86"}, {"TRADE_DT": "20260305", "PRODCD": "K015", "PRODNM": "자동차용부탄", "PRICE": "1012.20", "DIFF": "+0.04"}], "URL": "https://place.map.kakao.com/main/v/{}?_={}"}