{"OIL": [{"TRADE_DT": "20250723", "PRODCD": "B034", "PRODNM": "고급휘발유", "PRICE": "1919.22", "DIFF": "-0.32"}, {"TRADE_DT": "20250723", "PRODCD": "B027", "PRODNM": "휘발유", "PRICE": "1667.34", "DIFF": "-0.22"}, {"TRADE_DT": "20250723", "PRODCD": "D047", "PRODNM": "자동차용경유", "PRICE": "1531.70", "DIFF": "-0.13"}, {"TRADE_DT": "20250723", "PRODCD": "C004", "PRODNM": "실내등유", "PRICE": "1295.03", "DIFF": "-0.92"}, {"TRADE_DT": "20250723", "PRODCD": "K015", "PRODNM": "자동차용부탄", "PRICE": "1052.52", "DIFF": "-0.19"}], "URL": "https://place.map.kakao.com/main/v/{}?_={}"}