{"OIL": [{"TRADE_DT": "20230508", "PRODCD": "B034", "PRODNM": "고급휘발유", "PRICE": "1904.58", "DIFF": "+0.78"}, {"TRADE_DT": "20230508", "PRODCD": "B027", "PRODNM": "휘발유", "PRICE": "1653.57", "DIFF": "-0.53"}, {"TRADE_DT": "20230508", "PRODCD": "D047", "PRODNM": "자동차용경유", "PRICE": "1513.51", "DIFF": "-1.40"}, {"TRADE_DT": "20230508", "PRODCD": "C004", "PRODNM": "실내등유", "PRICE": "1394.28", "DIFF": "-0.23"}, {"TRADE_DT": "20230508", "PRODCD": "K015", "PRODNM": "자동차용부탄", "PRICE": "988.18", "DIFF": "-0.04"}], "URL": "https://place.map.kakao.com/main/v/{}?_={}"}